p55py/__init__.py
p55py/_version.py
p55py/example.py
p55py/static/extension.js
p55py/static/index.js
p55py/static/index.js.map
p55py-0.1.0.data/data/share/jupyter/nbextensions/p55py/extension.js
p55py-0.1.0.data/data/share/jupyter/nbextensions/p55py/index.js
p55py-0.1.0.data/data/share/jupyter/nbextensions/p55py/index.js.map
p55py-0.1.0.dist-info/DESCRIPTION.rst
p55py-0.1.0.dist-info/METADATA
p55py-0.1.0.dist-info/RECORD
p55py-0.1.0.dist-info/WHEEL
p55py-0.1.0.dist-info/metadata.json
p55py-0.1.0.dist-info/top_level.txt
